[
  {
    "id": "bbd2f2e2-6f1e-4a05-9c5a-fc53a3b89fa1",
    "name": "Payment Gateway API",
    "status": "ACTIVE",
    "type": "service"
  },
  {
    "id": "5f7c48a2-ffc2-4e1f-af2f-0e267305bb7e",
    "name": "Email Notification Service",
    "status": "DOWN",
    "type": "service"
  },
  {
    "id": "9a8f1df4-2ff2-40de-8ac3-9aa6f10dc439",
    "name": "User Authentication",
    "status": "ACTIVE",
    "type": "service"
  },
  {
    "id": "cfa7a544-3bc4-4b79-ae8c-ef0c37bcc19b",
    "name": "Data Analytics Engine",
    "status": "DOWN",
    "type": "service"
  },
  {
    "id": "e57e44ac-f1ef-4d9c-8713-6b26c93d54bc",
    "name": "Inventory Sync Service",
    "status": "DOWN",
    "type": "service"
  },
  {
    "id": "e9bdb7c3-84d6-48f1-9f54-644419542cdf",
    "name": "Mobile Push Gateway",
    "status": "DOWN",
    "type": "service"
  },
  {
    "id": "4f471f24-8719-4b1c-b7d4-302a55fc31e2",
    "name": "Order Processing Workflow",
    "status": "DOWN",
    "type": "service"
  },
  {
    "id": "38e62d36-b805-4b0e-88f8-1930b7eec874",
    "name": "Search Indexer",
    "status": "DOWN",
    "type": "service"
  },
  {
    "id": "d72c9ab4-a094-4af5-b71d-1fa19dfd4df7",
    "name": "Customer Support Chatbot",
    "status": "ACTIVE",
    "type": "service"
  },
  {
    "id": "bc7c465d-ff64-4e63-9c44-e1e9dc21a1f5",
    "name": "Billing Processor",
    "status": "DOWN",
    "type": "service"
  }
]
